netbox_topology_plugin_button/__init__.py
netbox_topology_plugin_button/template_content.py
netbox_topology_plugin_button/templates/netbox_topology_plugin_button/TopologyButton.html
netbox_topology_plugin_button-0.0.1.dist-info/METADATA
netbox_topology_plugin_button-0.0.1.dist-info/WHEEL
netbox_topology_plugin_button-0.0.1.dist-info/licenses/LICENSE
netbox_topology_plugin_button-0.0.1.dist-info/RECORD
